mseep_mcp_sound_tool-0.1.0.dist-info/licenses/LICENSE
src/__init__.py
src/sound_tool/__init__.py
src/sound_tool/server.py
src/sound_tool/tool_definition.py
tests/__init__.py
tests/test_sound_player.py
tests/test_sound_tool_server.py
mseep_mcp_sound_tool-0.1.0.dist-info/METADATA
mseep_mcp_sound_tool-0.1.0.dist-info/WHEEL
mseep_mcp_sound_tool-0.1.0.dist-info/top_level.txt
mseep_mcp_sound_tool-0.1.0.dist-info/RECORD
