Metadata-Version: 2.4
Name: mseep-mcp-sound-tool
Version: 0.1.0
Summary: An MCP server implementing a sound tool for Cursor and other MCP compatible IDEs
Home-page: https://github.com/mseep
Author: mseep
Author-email: support@skydeck.ai
Maintainer: mseep
Maintainer-email: support@skydeck.ai
Keywords: mseep
Classifier: Programming Language :: Python :: 3
Classifier: License :: OSI Approved :: MIT License
Classifier: Operating System :: OS Independent
Requires-Python: >=3.6
License-File: LICENSE
Requires-Dist: mcp<1.6.0,>=1.2.0
Dynamic: author
Dynamic: author-email
Dynamic: classifier
Dynamic: description
Dynamic: description-content-type
Dynamic: home-page
Dynamic: keywords
Dynamic: license-file
Dynamic: maintainer
Dynamic: maintainer-email
Dynamic: requires-dist
Dynamic: requires-python
Dynamic: summary
